inference/__init__.py
inference/predict.py
pages/File_Inference.py
pages/Sentence_Inference.py
pages/Training.py
pages/__init__.py
train/__init__.py
train/trainer.py
train/utils.py
CEFT_Classifier_French-0.1.dist-info/METADATA
CEFT_Classifier_French-0.1.dist-info/WHEEL
CEFT_Classifier_French-0.1.dist-info/top_level.txt
CEFT_Classifier_French-0.1.dist-info/RECORD
