Metadata-Version: 2.1
Name: CEFT-Classifier-French
Version: 0.1
Summary: A French text classification package.
Author: Jonathan Stefanov
Author-email: jonathan.stefanov@ik.me
Keywords: french text classification
Requires-Dist: pandas
Requires-Dist: torch
Requires-Dist: sentencepiece
Requires-Dist: transformers
Requires-Dist: torchvision
Requires-Dist: stqdm
Requires-Dist: streamlit
Requires-Dist: scikit-learn
Requires-Dist: wget
